jupyterlite_javascript_kernel/__init__.py
jupyterlite_javascript_kernel/_version.py
jupyterlite_javascript_kernel-0.3.0.data/data/share/jupyter/labextensions/@jupyterlite/javascript-kernel/package.json
jupyterlite_javascript_kernel-0.3.0.data/data/share/jupyter/labextensions/@jupyterlite/javascript-kernel/static/312.749011b8237164f040ce.js
jupyterlite_javascript_kernel-0.3.0.data/data/share/jupyter/labextensions/@jupyterlite/javascript-kernel/static/312.749011b8237164f040ce.js.LICENSE.txt
jupyterlite_javascript_kernel-0.3.0.data/data/share/jupyter/labextensions/@jupyterlite/javascript-kernel/static/584.7e49152bd31ca0f8291b.js
jupyterlite_javascript_kernel-0.3.0.data/data/share/jupyter/labextensions/@jupyterlite/javascript-kernel/static/584.7e49152bd31ca0f8291b.js.LICENSE.txt
jupyterlite_javascript_kernel-0.3.0.data/data/share/jupyter/labextensions/@jupyterlite/javascript-kernel/static/5e8d6f34d83488f083fd.png
jupyterlite_javascript_kernel-0.3.0.data/data/share/jupyter/labextensions/@jupyterlite/javascript-kernel/static/692.c1aeb4d97f766d3b4515.js
jupyterlite_javascript_kernel-0.3.0.data/data/share/jupyter/labextensions/@jupyterlite/javascript-kernel/static/692.c1aeb4d97f766d3b4515.js.LICENSE.txt
jupyterlite_javascript_kernel-0.3.0.data/data/share/jupyter/labextensions/@jupyterlite/javascript-kernel/static/804.fb6a8eda889cf61eea27.js
jupyterlite_javascript_kernel-0.3.0.data/data/share/jupyter/labextensions/@jupyterlite/javascript-kernel/static/b1c098fa349a030dacbe.png
jupyterlite_javascript_kernel-0.3.0.data/data/share/jupyter/labextensions/@jupyterlite/javascript-kernel/static/remoteEntry.6014628263d9ee9ca44a.js
jupyterlite_javascript_kernel-0.3.0.data/data/share/jupyter/labextensions/@jupyterlite/javascript-kernel/static/style.js
jupyterlite_javascript_kernel-0.3.0.data/data/share/jupyter/labextensions/@jupyterlite/javascript-kernel/static/third-party-licenses.json
jupyterlite_javascript_kernel-0.3.0.dist-info/METADATA
jupyterlite_javascript_kernel-0.3.0.dist-info/WHEEL
jupyterlite_javascript_kernel-0.3.0.dist-info/licenses/LICENSE
jupyterlite_javascript_kernel-0.3.0.dist-info/RECORD
