Metadata-Version: 2.3
Name: jupyterlite_javascript_kernel
Version: 0.3.0
Summary: A JavaScript kernel for JupyterLite
Project-URL: Homepage, https://github.com/jupyterlite/javascript-kernel
Project-URL: Bug Tracker, https://github.com/jupyterlite/javascript-kernel/issues
Project-URL: Repository, https://github.com/jupyterlite/javascript-kernel.git
Author: JupyterLite Contributors
License: BSD 3-Clause License
License-File: LICENSE
Classifier: Framework :: Jupyter
Classifier: Framework :: Jupyter :: JupyterLab
Classifier: Framework :: Jupyter :: JupyterLab :: 4
Classifier: Framework :: Jupyter :: JupyterLab :: Extensions
Classifier: Framework :: Jupyter :: JupyterLab :: Extensions :: Prebuilt
Classifier: License :: OSI Approved :: BSD License
Classifier: Programming Language :: Python
Classifier: Programming Language :: Python :: 3
Classifier: Programming Language :: Python :: 3.8
Classifier: Programming Language :: Python :: 3.9
Classifier: Programming Language :: Python :: 3.10
Classifier: Programming Language :: Python :: 3.11
Classifier: Programming Language :: Python :: 3.12
Requires-Python: >=3.8
